setup.py
blended_import_bootstrap.egg-info/PKG-INFO
blended_import_bootstrap.egg-info/SOURCES.txt
blended_import_bootstrap.egg-info/dependency_links.txt
blended_import_bootstrap.egg-info/not-zip-safe
blended_import_bootstrap.egg-info/requires.txt
blended_import_bootstrap.egg-info/top_level.txt
import_bootstrap/__init__.py